charsleft_widget/__init__.py
charsleft_widget/fields.py
charsleft_widget/models.py
charsleft_widget/widgets.py
charsleft_widget/locale/ru/LC_MESSAGES/django.mo
charsleft_widget/static/charsleft_widget/css/charsleft.css
charsleft_widget/static/charsleft_widget/css/charsleft.min.css
charsleft_widget/static/charsleft_widget/js/charsleft.js
charsleft_widget/static/charsleft_widget/js/charsleft.min.js
charsleft_widget/templates/charsleft_widget/charsleft_widget_css.html
charsleft_widget/templates/charsleft_widget/charsleft_widget_js.html
charsleft_widget/templates/charsleft_widget/textarea.html
charsleft_widget/templates/charsleft_widget/textarea.jinja
charsleft_widget/tests/__init__.py
charsleft_widget/tests/conftest.py
charsleft_widget/tests/models.py
charsleft_widget/tests/settings.py
charsleft_widget/tests/test_widgets.py
django_charsleft_widget-1.0.0.dist-info/LICENSE
django_charsleft_widget-1.0.0.dist-info/METADATA
django_charsleft_widget-1.0.0.dist-info/WHEEL
django_charsleft_widget-1.0.0.dist-info/top_level.txt
django_charsleft_widget-1.0.0.dist-info/RECORD
