Metadata-Version: 2.1
Name: django-charsleft-widget
Version: 1.0.0
Summary: Custom widget that limits the number of characters that can be entered in a textarea field
Home-page: https://github.com/bashu/django-charsleft-widget
Author: Basil Shubin
Author-email: basil.shubin@gmail.com
License: BSD License
Download-URL: https://github.com/bashu/django-charsleft-widget/zipball/master
Platform: UNKNOWN
Classifier: Development Status :: 5 - Production/Stable
Classifier: Environment :: Web Environment
Classifier: Intended Audience :: Developers
Classifier: License :: OSI Approved :: BSD License
Classifier: Operating System :: OS Independent
Classifier: Programming Language :: Python
Classifier: Programming Language :: Python :: 3 :: Only
Classifier: Programming Language :: Python :: 3.6
Classifier: Programming Language :: Python :: 3.7
Classifier: Programming Language :: Python :: 3.8
Classifier: Programming Language :: Python :: 3.9
Classifier: Framework :: Django
Classifier: Framework :: Django :: 2.2
Classifier: Framework :: Django :: 3.0
Classifier: Framework :: Django :: 3.1
Classifier: Framework :: Django :: 3.2
Classifier: Topic :: Internet :: WWW/HTTP
Classifier: Topic :: Internet :: WWW/HTTP :: Dynamic Content
Classifier: Topic :: Software Development :: Libraries :: Python Modules
License-File: LICENSE
Provides-Extra: develop
Requires-Dist: tox ; extra == 'develop'
Requires-Dist: django ; extra == 'develop'
Requires-Dist: pytest-django ; extra == 'develop'
Requires-Dist: pytest ; extra == 'develop'
Provides-Extra: test
Requires-Dist: pytest-django ; extra == 'test'
Requires-Dist: pytest-cov ; extra == 'test'
Requires-Dist: pytest ; extra == 'test'
